gpsd_prometheus_exporter/__init__.py
gpsd_prometheus_exporter/main.py
gpsd_prometheus_exporter-0.3.1.dist-info/entry_points.txt
gpsd_prometheus_exporter-0.3.1.dist-info/LICENSE
gpsd_prometheus_exporter-0.3.1.dist-info/WHEEL
gpsd_prometheus_exporter-0.3.1.dist-info/METADATA
gpsd_prometheus_exporter-0.3.1.dist-info/RECORD
