Metadata-Version: 2.1
Name: gpsd-prometheus-exporter
Version: 0.3.1
Summary: Monitor GPSD with Prometheus
License: MIT
Author: Mark S
Requires-Python: >=3.8,<4.0
Classifier: License :: OSI Approved :: MIT License
Classifier: Programming Language :: Python :: 3
Classifier: Programming Language :: Python :: 3.8
Classifier: Programming Language :: Python :: 3.9
Requires-Dist: argparse (>=1.4.0,<2.0.0)
Requires-Dist: bump2version (>=1.0.1,<2.0.0)
Requires-Dist: gps (>=3.19,<4.0)
Requires-Dist: gpsd-py3 (>=0.3.0,<0.4.0)
Requires-Dist: prometheus-client (>=0.9.0,<0.10.0)
